codegenerator/__init__.py
codegenerator/codegenerator.py
pycodecreator-0.0.1.dist-info/LICENSE
pycodecreator-0.0.1.dist-info/METADATA
pycodecreator-0.0.1.dist-info/WHEEL
pycodecreator-0.0.1.dist-info/top_level.txt
pycodecreator-0.0.1.dist-info/RECORD
