Metadata-Version: 2.1
Name: pycodecreator
Version: 0.0.1
Summary: A random code generator
Home-page: https://github.com/zahur76/randomcode
Author: zahur meerun
Author-email: zahurmeerun@hotmail.com
Project-URL: Bug Tracker, https://github.com/zahur76/randomcode/issues
Classifier: Programming Language :: Python :: 3
Classifier: License :: OSI Approved :: MIT License
Classifier: Operating System :: OS Independent
Requires-Python: >=3.6
License-File: LICENSE
